poe_api_wrapper/__init__.py
poe_api_wrapper/__main__.py
poe_api_wrapper/api.py
poe_api_wrapper/async_api.py
poe_api_wrapper/bundles.py
poe_api_wrapper/cli.py
poe_api_wrapper/example.py
poe_api_wrapper/llm.py
poe_api_wrapper/proxies.py
poe_api_wrapper/queries.py
poe_api_wrapper/utils.py
poe_api_wrapper-1.7.1.dist-info/LICENSE
poe_api_wrapper-1.7.1.dist-info/METADATA
poe_api_wrapper-1.7.1.dist-info/WHEEL
poe_api_wrapper-1.7.1.dist-info/entry_points.txt
poe_api_wrapper-1.7.1.dist-info/top_level.txt
poe_api_wrapper-1.7.1.dist-info/RECORD
