Metadata-Version: 2.1
Name: poe-api-wrapper
Version: 1.7.1
Summary: A simple, lightweight and efficient API wrapper for Poe.com
Home-page: https://github.com/snowby666/poe-api-wrapper
Author: snowby666
Keywords: python,poe,quora,chatgpt,claude,poe-api,api
Classifier: Programming Language :: Python :: 3
Classifier: License :: OSI Approved :: GNU General Public License (GPL)
Classifier: Operating System :: OS Independent
Requires-Python: >=3.7
License-File: LICENSE
Requires-Dist: httpx[http2]
Requires-Dist: websocket-client
Requires-Dist: requests-toolbelt
Requires-Dist: loguru
Requires-Dist: rich==13.3.4
Requires-Dist: beautifulsoup4
Requires-Dist: quickjs
Requires-Dist: nest-asyncio
Requires-Dist: orjson
Requires-Dist: aiofiles
Provides-Extra: llm
Requires-Dist: fastapi; extra == "llm"
Requires-Dist: pydantic; extra == "llm"
Requires-Dist: nltk; extra == "llm"
Requires-Dist: daphne; extra == "llm"
Requires-Dist: openai; extra == "llm"
Requires-Dist: Twisted[http2,tls]; extra == "llm"
Requires-Dist: tiktoken; extra == "llm"
Provides-Extra: proxy
Requires-Dist: numpy==1.26.4; extra == "proxy"
Requires-Dist: ballyregan; python_version >= "3.9" and extra == "proxy"
Provides-Extra: tests
Requires-Dist: tox; extra == "tests"
